libcde/__init__.py
libcde/libcde.py
libcde-0.0.2.dist-info/LICENSE
libcde-0.0.2.dist-info/METADATA
libcde-0.0.2.dist-info/WHEEL
libcde-0.0.2.dist-info/top_level.txt
libcde-0.0.2.dist-info/RECORD
